Metadata-Version: 1.0
Name: bithi-distributions
Version: 0.2
Summary: Gaussian distributions
Home-page: UNKNOWN
Author: Bithi
Author-email: UNKNOWN
License: UNKNOWN
Platform: UNKNOWN
